pyna/__init__.py
pyna/coord.py
pyna/field.py
pyna/flow.py
pyna/flowsol.py
pyna/flt.py
pyna/map.py
pyna/poincare.py
pyna/polymap.py
pyna/polynomial.py
pyna/sysutil.py
pyna/withparam.py
pyna_chaos-0.0.2.dist-info/LICENSE
pyna_chaos-0.0.2.dist-info/METADATA
pyna_chaos-0.0.2.dist-info/WHEEL
pyna_chaos-0.0.2.dist-info/top_level.txt
pyna_chaos-0.0.2.dist-info/RECORD
