Metadata-Version: 2.1
Name: pyna-chaos
Version: 0.0.2
Summary: Python package for DYNAmics (dynamical systems)
Home-page: https://github.com/WenyinWei/pyna
Author: Wenyin Wei
Author-email: wenyin.wei.ww@gmail.com
Classifier: Development Status :: 2 - Pre-Alpha
Classifier: Programming Language :: Python :: 3
Classifier: License :: OSI Approved :: GNU General Public License v3 or later (GPLv3+)
Classifier: Operating System :: OS Independent
Requires-Python: >=3.8
License-File: LICENSE
